<annotation>
	<folder></folder>
	<filename>Aldi_al_166186_PATATES FRITES 2_5KG04_07_17_27_56_schapkaart_jpg.rf.582f7f8f94e7d212b89b7f29597eab9f.jpg</filename>
	<path>Aldi_al_166186_PATATES FRITES 2_5KG04_07_17_27_56_schapkaart_jpg.rf.582f7f8f94e7d212b89b7f29597eab9f.jpg</path>
	<source>
		<database>roboflow.ai</database>
	</source>
	<size>
		<width>416</width>
		<height>416</height>
		<depth>3</depth>
	</size>
	<segmented>0</segmented>
	<object>
		<name>prtg</name>
		<pose>Unspecified</pose>
		<truncated>0</truncated>
		<difficult>0</difficult>
		<occluded>0</occluded>
		<bndbox>
			<xmin>99</xmin>
			<xmax>319</xmax>
			<ymin>196</ymin>
			<ymax>268</ymax>
		</bndbox>
	</object>
</annotation>
