<annotation>
	<folder></folder>
	<filename>Lidl_li_245382_Zwagerman gerookte spekreepjes04_07_18_00_05_schapkaart_jpg.rf.61b43047a0bd2bfe3b00d00a585678ef.jpg</filename>
	<path>Lidl_li_245382_Zwagerman gerookte spekreepjes04_07_18_00_05_schapkaart_jpg.rf.61b43047a0bd2bfe3b00d00a585678ef.jpg</path>
	<source>
		<database>roboflow.ai</database>
	</source>
	<size>
		<width>416</width>
		<height>416</height>
		<depth>3</depth>
	</size>
	<segmented>0</segmented>
	<object>
		<name>prtg</name>
		<pose>Unspecified</pose>
		<truncated>0</truncated>
		<difficult>0</difficult>
		<occluded>0</occluded>
		<bndbox>
			<xmin>61</xmin>
			<xmax>409</xmax>
			<ymin>164</ymin>
			<ymax>250</ymax>
		</bndbox>
	</object>
</annotation>
