<annotation>
	<folder />
	<filename>Lidl_li_191618_Floralys Keukenrollen 3-laags 4x 53vel27_06_17_33_24_schapkaart_jpg.rf.9d459f1dec5f1ed0f15d5ad5371b2652.jpg</filename>
	<path>Lidl_li_191618_Floralys Keukenrollen 3-laags 4x 53vel27_06_17_33_24_schapkaart_jpg.rf.9d459f1dec5f1ed0f15d5ad5371b2652.jpg</path>
	<source>
		<database>roboflow.ai</database>
	</source>
	<size>
		<width>416</width>
		<height>416</height>
		<depth>3</depth>
	</size>
	<segmented>0</segmented>
	<object>
		<name>prtg</name>
		<pose>Unspecified</pose>
		<truncated>0</truncated>
		<difficult>0</difficult>
		<occluded>0</occluded>
		<bndbox>
			<xmin>92</xmin>
			<xmax>117</xmax>
			<ymin>34</ymin>
			<ymax>66</ymax>
		</bndbox>
	</object>
	<object>
		<name>prtg</name>
		<pose>Unspecified</pose>
		<truncated>0</truncated>
		<difficult>0</difficult>
		<occluded>0</occluded>
		<bndbox>
			<xmin>220</xmin>
			<xmax>251</xmax>
			<ymin>14</ymin>
			<ymax>50</ymax>
		</bndbox>
	</object>
	<object>
		<name>prtg</name>
		<pose>Unspecified</pose>
		<truncated>0</truncated>
		<difficult>0</difficult>
		<occluded>0</occluded>
		<bndbox>
			<xmin>392</xmin>
			<xmax>415</xmax>
			<ymin>1</ymin>
			<ymax>30</ymax>
		</bndbox>
	</object>
	<object>
		<name>prtg</name>
		<pose>Unspecified</pose>
		<truncated>0</truncated>
		<difficult>0</difficult>
		<occluded>0</occluded>
		<bndbox>
			<xmin>38</xmin>
			<xmax>58</xmax>
			<ymin>90</ymin>
			<ymax>114</ymax>
		</bndbox>
	</object>
	<object>
		<name>prtg</name>
		<pose>Unspecified</pose>
		<truncated>0</truncated>
		<difficult>0</difficult>
		<occluded>0</occluded>
		<bndbox>
			<xmin>1</xmin>
			<xmax>14</xmax>
			<ymin>94</ymin>
			<ymax>117</ymax>
		</bndbox>
	</object>
	<object>
		<name>prtg</name>
		<pose>Unspecified</pose>
		<truncated>0</truncated>
		<difficult>0</difficult>
		<occluded>0</occluded>
		<bndbox>
			<xmin>16</xmin>
			<xmax>41</xmax>
			<ymin>161</ymin>
			<ymax>167</ymax>
		</bndbox>
	</object>
</annotation>