<annotation>
	<folder />
	<filename>Lidl_li_105649_Belbake Kristalsuiker31_05_15_46_44_schapkaart_jpg.rf.54b53d4fef817df196d7480088867688.jpg</filename>
	<path>Lidl_li_105649_Belbake Kristalsuiker31_05_15_46_44_schapkaart_jpg.rf.54b53d4fef817df196d7480088867688.jpg</path>
	<source>
		<database>roboflow.ai</database>
	</source>
	<size>
		<width>416</width>
		<height>416</height>
		<depth>3</depth>
	</size>
	<segmented>0</segmented>
	<object>
		<name>prtg</name>
		<pose>Unspecified</pose>
		<truncated>0</truncated>
		<difficult>0</difficult>
		<occluded>0</occluded>
		<bndbox>
			<xmin>98</xmin>
			<xmax>258</xmax>
			<ymin>60</ymin>
			<ymax>95</ymax>
		</bndbox>
	</object>
</annotation>